cryptoxlib/CryptoXLib.py
cryptoxlib/CryptoXLibClient.py
cryptoxlib/Pair.py
cryptoxlib/PeriodicChecker.py
cryptoxlib/Timer.py
cryptoxlib/WebsocketMgr.py
cryptoxlib/__init__.py
cryptoxlib/exceptions.py
cryptoxlib/version_conversions.py
cryptoxlib/clients/__init__.py
cryptoxlib/clients/aax/AAXClient.py
cryptoxlib/clients/aax/AAXWebsocket.py
cryptoxlib/clients/aax/__init__.py
cryptoxlib/clients/aax/enums.py
cryptoxlib/clients/aax/exceptions.py
cryptoxlib/clients/aax/functions.py
cryptoxlib/clients/bibox/BiboxClient.py
cryptoxlib/clients/bibox/BiboxWebsocket.py
cryptoxlib/clients/bibox/__init__.py
cryptoxlib/clients/bibox/enums.py
cryptoxlib/clients/bibox/exceptions.py
cryptoxlib/clients/bibox/functions.py
cryptoxlib/clients/bibox_europe/BiboxEuropeClient.py
cryptoxlib/clients/bibox_europe/BiboxEuropeWebsocket.py
cryptoxlib/clients/bibox_europe/__init__.py
cryptoxlib/clients/bibox_europe/enums.py
cryptoxlib/clients/bibox_europe/exceptions.py
cryptoxlib/clients/bibox_europe/functions.py
cryptoxlib/clients/binance/BinanceClient.py
cryptoxlib/clients/binance/BinanceCommonClient.py
cryptoxlib/clients/binance/BinanceCommonWebsocket.py
cryptoxlib/clients/binance/BinanceFuturesClient.py
cryptoxlib/clients/binance/BinanceFuturesWebsocket.py
cryptoxlib/clients/binance/BinanceWebsocket.py
cryptoxlib/clients/binance/__init__.py
cryptoxlib/clients/binance/enums.py
cryptoxlib/clients/binance/exceptions.py
cryptoxlib/clients/binance/functions.py
cryptoxlib/clients/binance/types.py
cryptoxlib/clients/bitforex/BitforexClient.py
cryptoxlib/clients/bitforex/BitforexWebsocket.py
cryptoxlib/clients/bitforex/__init__.py
cryptoxlib/clients/bitforex/enums.py
cryptoxlib/clients/bitforex/exceptions.py
cryptoxlib/clients/bitforex/functions.py
cryptoxlib/clients/bitpanda/BitpandaClient.py
cryptoxlib/clients/bitpanda/BitpandaWebsocket.py
cryptoxlib/clients/bitpanda/__init__.py
cryptoxlib/clients/bitpanda/enums.py
cryptoxlib/clients/bitpanda/exceptions.py
cryptoxlib/clients/bitpanda/functions.py
cryptoxlib_aio-5.3.0.dist-info/LICENSE
cryptoxlib_aio-5.3.0.dist-info/METADATA
cryptoxlib_aio-5.3.0.dist-info/WHEEL
cryptoxlib_aio-5.3.0.dist-info/top_level.txt
cryptoxlib_aio-5.3.0.dist-info/RECORD
