Metadata-Version: 2.1
Name: cryptoxlib-aio
Version: 5.3.0
Summary: Cryptoexchange asynchronous python client
Home-page: https://github.com/nardew/cryptoxlib-aio
Author: nardew
Author-email: cryptoxlib.aio@gmail.com
License: UNKNOWN
Platform: UNKNOWN
Classifier: Development Status :: 5 - Production/Stable
Classifier: Framework :: AsyncIO
Classifier: Intended Audience :: Developers
Classifier: Programming Language :: Python :: 3
Classifier: Programming Language :: Python :: 3.6
Classifier: Programming Language :: Python :: 3.7
Classifier: Programming Language :: Python :: 3.8
Classifier: Programming Language :: Python :: 3.9
Classifier: Programming Language :: Python :: 3.10
Classifier: License :: OSI Approved :: MIT License
Classifier: Operating System :: OS Independent
Classifier: Topic :: Software Development :: Libraries
Classifier: Topic :: Software Development :: Libraries :: Python Modules
Classifier: Typing :: Typed
Requires-Python: >=3.6.1
License-File: LICENSE
Requires-Dist: aiohttp (==3.7.4)
Requires-Dist: websockets (==9.1)
Requires-Dist: PyJWT (==2.4.0)
Requires-Dist: pytz (==2019.3)
